json_repair_tool/__init__.py
json_repair_tool/core.py
json_repair_tool/validators.py
json_repair_tool-0.1.1.dist-info/WHEEL
json_repair_tool-0.1.1.dist-info/entry_points.txt
json_repair_tool-0.1.1.dist-info/METADATA
json_repair_tool-0.1.1.dist-info/RECORD
