Metadata-Version: 2.3
Name: json-repair-tool
Version: 0.1.1
Summary: Repair broken JSON and coerce messy LLM outputs into strict Pydantic models.
Keywords: ai,llm,json,pydantic,parsing,openai,rag
Author: Jamessdevops
Author-email: Jamessdevops <subzerotamil2@gmail.com>
Requires-Dist: pydantic>=2.0.0
Requires-Dist: json-repair>=0.25.0
Requires-Python: >=3.10
